ihp_hdl21/__init__.py
ihp_hdl21/pdk_data.py
ihp_hdl21/pdk_logic.py
ihp_hdl21/test_pdk.py
ihp_hdl21/test_site_sims.py
ihp_hdl21/digital_cells/__init__.py
ihp_hdl21/digital_cells/stdcells.py
ihp_hdl21/primitives/__init__.py
ihp_hdl21/primitives/prim_dicts.py
ihp_hdl21/primitives/primitives.py
ihp_hdl21-7.0.0.dist-info/licenses/LICENSE
ihp_hdl21-7.0.0.dist-info/WHEEL
ihp_hdl21-7.0.0.dist-info/METADATA
ihp_hdl21-7.0.0.dist-info/RECORD
