Metadata-Version: 2.4
Name: ihp-hdl21
Version: 7.0.0
Summary: IHP SG13G2 130nm BiCMOS PDK Package for Hdl21
Keywords: PDK,EDA,analog,circuit,BiCMOS,HBT,RF
Author: Thomas Pluck
Maintainer: Thomas Pluck
Requires-Python: >=3.7, <3.13
Classifier: Development Status :: 4 - Beta
Classifier: Programming Language :: Python
Classifier: Topic :: Scientific/Engineering :: Electronic Design Automation (EDA)
License-File: LICENSE
Requires-Dist: hdl21>=7.0.0
Requires-Dist: vlsirdev ; extra == "dev"
Project-URL: Bug Tracker, https://github.com/dan-fritchman/Hdl21/issues
Project-URL: Documentation, https://github.com/dan-fritchman/Hdl21/blob/main/pdks/IHP/readme.md
Project-URL: Homepage, https://github.com/dan-fritchman/Hdl21
Project-URL: Repository, https://github.com/dan-fritchman/Hdl21
Provides-Extra: dev
